{"stats":{"minecraft:killed_by":{"minecraft:zombie":2,"minecraft:creeper":1,"minecraft:drowned":1,"minecraft:skeleton":1},"minecraft:custom":{"minecraft:interact_with_crafting_table":288,"minecraft:bell_ring":403,"minecraft:leave_game":24,"minecraft:time_since_death":185462,"minecraft:damage_blocked_by_shield":3947,"minecraft:play_time":2074485,"minecraft:deaths":25,"minecraft:jump":41843,"minecraft:enchant_item":59,"minecraft:interact_with_furnace":332,"minecraft:traded_with_villager":804,"minecraft:sleep_in_bed":21,"minecraft:damage_dealt":202681,"minecraft:interact_with_smoker":15,"minecraft:horse_one_cm":327144,"minecraft:interact_with_smithing_table":19,"minecraft:interact_with_anvil":76,"minecraft:inspect_hopper":15,"minecraft:sneak_time":178310,"minecraft:interact_with_blast_furnace":51,"minecraft:total_world_time":2074485,"minecraft:time_since_rest":38806,"minecraft:swim_one_cm":2744128,"minecraft:fly_one_cm":7891094,"minecraft:open_chest":2922,"minecraft:fall_one_cm":1021939,"minecraft:sprint_one_cm":8808671,"minecraft:drop":2380,"minecraft:talked_to_villager":350,"minecraft:interact_with_brewingstand":63,"minecraft:walk_on_water_one_cm":303778,"minecraft:interact_with_loom":21,"minecraft:open_enderchest":572,"minecraft:interact_with_beacon":8,"minecraft:player_kills":3,"minecraft:crouch_one_cm":572922,"minecraft:mob_kills":4712,"minecraft:climb_one_cm":161034,"minecraft:walk_one_cm":2741656,"minecraft:raid_win":5,"minecraft:walk_under_water_one_cm":2454808,"minecraft:boat_one_cm":1509092,"minecraft:raid_trigger":1,"minecraft:interact_with_grindstone":37,"minecraft:damage_taken":38112,"minecraft:damage_absorbed":60},"minecraft:killed":{"minecraft:cod":3,"minecraft:pufferfish":1,"minecraft:skeleton":1327,"minecraft:chicken":6,"minecraft:magma_cube":119,"minecraft:iron_golem":10,"minecraft:pillager":36,"minecraft:donkey":2,"minecraft:zombie":1317,"minecraft:cow":74,"minecraft:evoker":2,"minecraft:vindicator":13,"minecraft:endermite":1,"minecraft:horse":13,"minecraft:ravager":1,"minecraft:enderman":74,"minecraft:witch":30,"minecraft:spider":51,"minecraft:wither":1,"minecraft:piglin":36,"minecraft:pig":20,"minecraft:zombie_villager":20,"minecraft:creeper":1329,"minecraft:sheep":16,"minecraft:ghast":11,"minecraft:stray":7,"minecraft:blaze":60,"minecraft:vex":1,"minecraft:phantom":21,"minecraft:drowned":4,"minecraft:wither_skeleton":38},"minecraft:crafted":{"minecraft:ender_chest":4,"minecraft:smooth_stone":8,"minecraft:blaze_powder":54,"minecraft:birch_boat":1,"minecraft:loom":3,"minecraft:diamond_shovel":3,"minecraft:bookshelf":103,"minecraft:glass":40,"minecraft:diamond_helmet":3,"minecraft:diamond_leggings":3,"minecraft:beacon":1,"minecraft:glass_bottle":27,"minecraft:emerald":774,"minecraft:cooked_porkchop":5,"minecraft:diamond_axe":5,"minecraft:spruce_door":6,"minecraft:smithing_table":1,"minecraft:golden_pickaxe":1,"minecraft:fletching_table":7,"minecraft:stone_brick_stairs":16,"minecraft:stone_slab":408,"minecraft:iron_pickaxe":1,"minecraft:iron_block":79,"minecraft:gold_ingot":212,"minecraft:netherite_ingot":5,"minecraft:composter":3,"minecraft:packed_ice":86,"minecraft:golden_carrot":309,"minecraft:red_banner":3,"minecraft:bone_meal":7442,"minecraft:white_carpet":3,"minecraft:diamond":18,"minecraft:spruce_stairs":92,"minecraft:ladder":48,"minecraft:spruce_slab":156,"minecraft:stone_pickaxe":4,"minecraft:diamond_boots":3,"minecraft:cobbled_deepslate_stairs":152,"minecraft:spruce_boat":3,"minecraft:enchanting_table":1,"minecraft:enchanted_book":29,"minecraft:orange_dye":22,"minecraft:flint":10,"minecraft:iron_leggings":2,"minecraft:oak_planks":492,"minecraft:cobblestone_slab":486,"minecraft:cobblestone_stairs":128,"minecraft:stone":51,"minecraft:flower_banner_pattern":10,"minecraft:warped_planks":92,"minecraft:hopper":15,"minecraft:stone_brick_slab":30,"minecraft:bow":22,"minecraft:iron_boots":2,"minecraft:chest":59,"minecraft:netherite_upgrade_smithing_template":6,"minecraft:stone_hoe":5,"minecraft:ender_eye":9,"minecraft:stone_bricks":324,"minecraft:smoker":1,"minecraft:white_banner":1,"minecraft:arrow":4,"minecraft:crafting_table":19,"minecraft:spruce_planks":10628,"minecraft:wooden_pickaxe":1,"minecraft:baked_potato":384,"minecraft:iron_helmet":2,"minecraft:brewing_stand":9,"minecraft:birch_planks":12,"minecraft:tnt":55,"minecraft:spruce_trapdoor":230,"minecraft:iron_chestplate":2,"minecraft:book":18,"minecraft:paper":666,"minecraft:diamond_pickaxe":8,"minecraft:yellow_dye":24,"minecraft:shield":4,"minecraft:stick":17348,"minecraft:iron_ingot":605,"minecraft:shears":1,"minecraft:cobbled_deepslate_slab":144,"minecraft:furnace":8,"minecraft:blast_furnace":3,"minecraft:diamond_block":2,"minecraft:flint_and_steel":2,"minecraft:iron_axe":1,"minecraft:netherite_scrap":23,"minecraft:cooked_beef":30,"minecraft:sugar":145,"minecraft:red_dye":23,"minecraft:diamond_sword":6,"minecraft:iron_sword":1,"minecraft:bucket":14,"minecraft:acacia_boat":1,"minecraft:bread":199,"minecraft:air":0,"minecraft:oak_boat":5,"minecraft:gold_nugget":1908,"minecraft:anvil":3,"minecraft:acacia_planks":12,"minecraft:torch":224,"minecraft:diamond_chestplate":4},"minecraft:used":{"minecraft:moss_block":17,"minecraft:nether_brick_fence":3,"minecraft:spruce_slab":144,"minecraft:ladder":35,"minecraft:poppy":11,"minecraft:chest":69,"minecraft:stone":152,"minecraft:rotten_flesh":73,"minecraft:soul_sand":27,"minecraft:lily_of_the_valley":4,"minecraft:spruce_boat":14,"minecraft:packed_ice":93,"minecraft:lava_bucket":10,"minecraft:grass_block":2186,"minecraft:copper_ore":2,"minecraft:dark_oak_slab":1,"minecraft:stone_brick_stairs":22,"minecraft:netherite_boots":1,"minecraft:bow":667,"minecraft:sweet_berries":95,"minecraft:oak_sapling":4,"minecraft:furnace":12,"minecraft:potato":185,"minecraft:mossy_stone_bricks":3,"minecraft:diorite":28,"minecraft:leather_leggings":1,"minecraft:spruce_door":12,"minecraft:blackstone":1,"minecraft:wooden_pickaxe":9,"minecraft:composter":2,"minecraft:clay":1,"minecraft:oak_leaves":1,"minecraft:golden_apple":2,"minecraft:sand":19,"minecraft:blast_furnace":3,"minecraft:blue_ice":2,"minecraft:netherite_helmet":3,"minecraft:deepslate_iron_ore":14,"minecraft:lectern":73,"minecraft:diamond_sword":1567,"minecraft:smithing_table":5,"minecraft:ice":1,"minecraft:oak_boat":19,"minecraft:enchanting_table":2,"minecraft:armor_stand":1,"minecraft:netherrack":3037,"minecraft:torch":79,"minecraft:brewing_stand":19,"minecraft:warped_wart_block":6,"minecraft:anvil":6,"minecraft:nether_quartz_ore":3,"minecraft:twisting_vines":1,"minecraft:flowering_azalea":2,"minecraft:chipped_anvil":2,"minecraft:iron_axe":18,"minecraft:iron_block":103,"minecraft:bamboo":7,"minecraft:diamond_chestplate":2,"minecraft:basalt":11,"minecraft:cobbled_deepslate":75,"minecraft:acacia_planks":8,"minecraft:cherry_log":3,"minecraft:wheat_seeds":619,"minecraft:water_bucket":979,"minecraft:fletching_table":6,"minecraft:cracked_stone_bricks":1,"minecraft:mossy_cobblestone":9,"minecraft:diamond_block":2,"minecraft:rail":2,"minecraft:oak_slab":3,"minecraft:tnt":53,"minecraft:crafting_table":29,"minecraft:white_bed":1,"minecraft:cod":3,"minecraft:spruce_log":107,"minecraft:ender_eye":2,"minecraft:diamond_pickaxe":12057,"minecraft:diamond_shovel":3769,"minecraft:mangrove_propagule":7,"minecraft:iron_pickaxe":38,"minecraft:spruce_trapdoor":278,"minecraft:spruce_sapling":13,"minecraft:cobblestone":452,"minecraft:purple_bed":26,"minecraft:cooked_porkchop":22,"minecraft:porkchop":1,"minecraft:kelp":616,"minecraft:diamond_leggings":3,"minecraft:cherry_sapling":2,"minecraft:shield":86,"minecraft:iron_sword":443,"minecraft:nether_wart":16,"minecraft:iron_chestplate":1,"minecraft:spruce_leaves":24,"minecraft:mutton":11,"minecraft:nether_bricks":94,"minecraft:carrot":2332,"minecraft:tuff":51,"minecraft:axolotl_bucket":31,"minecraft:big_dripleaf":10,"minecraft:obsidian":23,"minecraft:glass":10,"minecraft:coal_ore":59,"minecraft:warped_nylium":41,"minecraft:iron_helmet":2,"minecraft:stone_bricks":175,"minecraft:deepslate_diamond_ore":87,"minecraft:magma_block":2,"minecraft:warped_fungus":1,"minecraft:diamond_boots":5,"minecraft:wither_skeleton_skull":3,"minecraft:stone_pickaxe":400,"minecraft:oak_planks":25,"minecraft:ender_pearl":88,"minecraft:blue_bed":22,"minecraft:diamond_axe":2513,"minecraft:sugar_cane":5,"minecraft:netherite_leggings":3,"minecraft:loom":4,"minecraft:crossbow":1,"minecraft:deepslate_lapis_ore":31,"minecraft:cobbled_deepslate_stairs":116,"minecraft:deepslate":313,"minecraft:gravel":44,"minecraft:golden_helmet":1,"minecraft:grindstone":3,"minecraft:andesite":28,"minecraft:bone_meal":7347,"minecraft:golden_pickaxe":32,"minecraft:oak_fence":1,"minecraft:netherite_sword":2233,"minecraft:flint_and_steel":45,"minecraft:spruce_planks":48,"minecraft:ender_chest":62,"minecraft:deepslate_gold_ore":87,"minecraft:stone_hoe":62,"minecraft:dirt":523,"minecraft:white_carpet":2,"minecraft:hopper":16,"minecraft:spruce_stairs":50,"minecraft:cobblestone_wall":1,"minecraft:diamond_helmet":3,"minecraft:spruce_fence":6,"minecraft:granite":16,"minecraft:stone_brick_slab":13,"minecraft:bookshelf":93,"minecraft:iron_boots":2,"minecraft:golden_carrot":188,"minecraft:cooked_beef":126,"minecraft:iron_leggings":2,"minecraft:cooked_mutton":9,"minecraft:acacia_boat":2,"minecraft:iron_ore":3,"minecraft:cobblestone_stairs":45,"minecraft:glass_bottle":27,"minecraft:netherite_chestplate":1,"minecraft:baked_potato":100,"minecraft:birch_boat":8,"minecraft:brown_mushroom":1,"minecraft:beacon":2,"minecraft:cobblestone_slab":434,"minecraft:warped_roots":16,"minecraft:smoker":1,"minecraft:nether_gold_ore":64,"minecraft:black_wool":1,"minecraft:netherite_axe":2181,"minecraft:lapis_ore":6,"minecraft:stone_slab":406,"minecraft:cobbled_deepslate_slab":70,"minecraft:white_banner":6,"minecraft:red_banner":14,"minecraft:bucket":1038,"minecraft:splash_potion":3},"minecraft:broken":{"minecraft:diamond_pickaxe":1,"minecraft:iron_sword":1,"minecraft:stone_pickaxe":3,"minecraft:golden_pickaxe":1},"minecraft:picked_up":{"minecraft:anvil":2,"minecraft:flower_pot":1,"minecraft:smithing_table":4,"minecraft:stone_slab":11,"minecraft:diamond_sword":11,"minecraft:enchanted_book":4,"minecraft:brewing_stand":10,"minecraft:golden_sword":2,"minecraft:string":83,"minecraft:cooked_salmon":4,"minecraft:pufferfish":2,"minecraft:diamond_leggings":4,"minecraft:gold_nugget":679,"minecraft:cobbled_deepslate":866,"minecraft:spruce_planks":532,"minecraft:flower_banner_pattern":4,"minecraft:netherite_upgrade_smithing_template":6,"minecraft:golden_helmet":1,"minecraft:spruce_pressure_plate":2,"minecraft:big_dripleaf":10,"minecraft:acacia_log":3,"minecraft:cherry_log":4,"minecraft:warped_planks":32,"minecraft:golden_chestplate":2,"minecraft:cauldron":4,"minecraft:stone_sword":2,"minecraft:iron_block":33,"minecraft:bookshelf":60,"minecraft:netherite_chestplate":1,"minecraft:blaze_rod":193,"minecraft:birch_log":3,"minecraft:magma_block":84,"minecraft:feather":37,"minecraft:cooked_beef":149,"minecraft:water_bucket":18,"minecraft:flint":20,"minecraft:netherite_leggings":1,"minecraft:twisting_vines":27,"minecraft:purple_carpet":5,"minecraft:chipped_anvil":2,"minecraft:diamond_helmet":4,"minecraft:glowstone_dust":96,"minecraft:moss_block":17,"minecraft:warped_wart_block":9,"minecraft:loom":1,"minecraft:deepslate":398,"minecraft:deepslate_gold_ore":174,"minecraft:blue_ice":57,"minecraft:granite":21,"minecraft:bread":34,"minecraft:jack_o_lantern":4,"minecraft:diamond_pickaxe":12,"minecraft:spruce_leaves":36,"minecraft:mud":13,"minecraft:crafting_table":18,"minecraft:bee_nest":2,"minecraft:nether_wart":70,"minecraft:leather_leggings":4,"minecraft:flint_and_steel":3,"minecraft:white_carpet":11,"minecraft:glass_pane":26,"minecraft:cracked_stone_bricks":10,"minecraft:netherite_sword":1,"minecraft:deepslate_diamond_ore":110,"minecraft:beef":85,"minecraft:poppy":50,"minecraft:spruce_slab":332,"minecraft:chest":25,"minecraft:copper_ore":3,"minecraft:stone":1339,"minecraft:spruce_fence":117,"minecraft:carrot":8403,"minecraft:redstone":3,"minecraft:tnt":114,"minecraft:diamond_chestplate":4,"minecraft:diamond_boots":5,"minecraft:gold_ingot":7,"minecraft:totem_of_undying":7,"minecraft:mutton":27,"minecraft:white_wool":17,"minecraft:rail":2,"minecraft:oxeye_daisy":12,"minecraft:lapis_ore":12,"minecraft:fern":1,"minecraft:yellow_dye":4,"minecraft:red_mushroom":3,"minecraft:filled_map":2,"minecraft:oak_log":48,"minecraft:ancient_debris":35,"minecraft:blue_bed":21,"minecraft:white_banner":12,"minecraft:stone_bricks":203,"minecraft:kelp":1735,"minecraft:warped_stem":25,"minecraft:stone_pickaxe":3,"minecraft:iron_ore":3,"minecraft:glass_bottle":3,"minecraft:iron_sword":2,"minecraft:flowering_azalea":6,"minecraft:dark_oak_slab":1,"minecraft:sweet_berries":205,"minecraft:red_wool":20,"minecraft:gravel":124,"minecraft:spruce_sapling":70,"minecraft:spruce_log":2936,"minecraft:leather_helmet":1,"minecraft:diamond_shovel":3,"minecraft:coal_ore":94,"minecraft:purple_bed":21,"minecraft:rib_armor_trim_smithing_template":1,"minecraft:diamond_axe":8,"minecraft:warped_roots":37,"minecraft:baked_potato":2,"minecraft:warped_nylium":62,"minecraft:mangrove_propagule":7,"minecraft:hopper":18,"minecraft:ender_pearl":204,"minecraft:wheat":600,"minecraft:nether_brick_fence":3,"minecraft:ender_chest":63,"minecraft:potion":8,"minecraft:stone_brick_stairs":22,"minecraft:raw_copper":33,"minecraft:deepslate_lapis_ore":31,"minecraft:netherite_ingot":3,"minecraft:armor_stand":1,"minecraft:smooth_stone":1,"minecraft:bucket":2,"minecraft:red_dye":10,"minecraft:cobblestone_slab":259,"minecraft:ender_eye":1,"minecraft:azalea":1,"minecraft:deepslate_iron_ore":14,"minecraft:furnace":14,"minecraft:tipped_arrow":4,"minecraft:stick":328,"minecraft:oak_fence":8,"minecraft:torch":311,"minecraft:spruce_stairs":90,"minecraft:porkchop":6,"minecraft:snow_block":4,"minecraft:diorite":99,"minecraft:nether_gold_ore":64,"minecraft:rotten_flesh":839,"minecraft:mangrove_roots":1,"minecraft:obsidian":180,"minecraft:cod":3,"minecraft:cobblestone":1965,"minecraft:blaze_powder":2,"minecraft:enchanting_table":1,"minecraft:leather_chestplate":2,"minecraft:magma_cream":55,"minecraft:andesite":39,"minecraft:golden_leggings":1,"minecraft:beacon":1,"minecraft:potato":632,"minecraft:tuff":83,"minecraft:acacia_boat":1,"minecraft:wither_skeleton_skull":3,"minecraft:dirt":992,"minecraft:lapis_lazuli":633,"minecraft:leather_boots":2,"minecraft:glass":28,"minecraft:bone":2017,"minecraft:acacia_planks":7,"minecraft:bow":89,"minecraft:wheat_seeds":1745,"minecraft:cobbled_deepslate_slab":16,"minecraft:raw_gold":126,"minecraft:bell":1,"minecraft:grindstone":3,"minecraft:netherite_axe":1,"minecraft:mossy_stone_bricks":7,"minecraft:fletching_table":2,"minecraft:bamboo":28,"minecraft:oak_planks":16,"minecraft:stone_hoe":3,"minecraft:ghast_tear":3,"minecraft:cooked_porkchop":71,"minecraft:poisonous_potato":2,"minecraft:sand":323,"minecraft:jungle_planks":2,"minecraft:diamond_block":2,"minecraft:grass_block":2530,"minecraft:lily_of_the_valley":5,"minecraft:mossy_cobblestone":94,"minecraft:sugar":2,"minecraft:clay":46,"minecraft:diamond":313,"minecraft:spruce_boat":15,"minecraft:netherite_helmet":2,"minecraft:crossbow":11,"minecraft:bone_meal":91,"minecraft:golden_apple":1,"minecraft:spruce_sign":2,"minecraft:emerald":33,"minecraft:oak_sapling":5,"minecraft:netherrack":8702,"minecraft:oak_leaves":1,"minecraft:nether_star":1,"minecraft:chicken":25,"minecraft:ladder":50,"minecraft:packed_ice":116,"minecraft:brown_mushroom":35,"minecraft:gold_block":1,"minecraft:shield":3,"minecraft:oak_trapdoor":1,"minecraft:moss_carpet":5,"minecraft:iron_axe":2,"minecraft:blackstone":59,"minecraft:oak_boat":16,"minecraft:lectern":72,"minecraft:sugar_cane":883,"minecraft:phantom_membrane":5,"minecraft:spruce_trapdoor":411,"minecraft:raw_iron":35,"minecraft:copper_ingot":1,"minecraft:cookie":2,"minecraft:arrow":1468,"minecraft:pumpkin_pie":1,"minecraft:nether_bricks":103,"minecraft:netherite_boots":1,"minecraft:basalt":86,"minecraft:golden_carrot":29,"minecraft:glow_ink_sac":2,"minecraft:salmon":1,"minecraft:cut_sandstone":2,"minecraft:leather":172,"minecraft:ice":782,"minecraft:cobblestone_wall":12,"minecraft:cobbled_deepslate_stairs":62,"minecraft:gunpowder":696,"minecraft:cobblestone_stairs":29,"minecraft:cooked_mutton":14,"minecraft:rabbit_hide":1,"minecraft:iron_ingot":135,"minecraft:cooked_chicken":1,"minecraft:soul_sand":58,"minecraft:acacia_sapling":1,"minecraft:book":863,"minecraft:warped_fungus":2,"minecraft:nether_quartz_ore":3,"minecraft:birch_boat":8,"minecraft:pumpkin":51,"minecraft:stone_brick_slab":22,"minecraft:quartz":359,"minecraft:dandelion":24,"minecraft:red_banner":18,"minecraft:white_bed":1,"minecraft:spruce_door":24,"minecraft:spider_eye":60,"minecraft:campfire":2,"minecraft:iron_helmet":2,"minecraft:cherry_sapling":2,"minecraft:black_wool":1,"minecraft:coal":449},"minecraft:mined":{"minecraft:white_bed":1,"minecraft:cherry_log":4,"minecraft:jungle_leaves":1,"minecraft:obsidian":109,"minecraft:granite":21,"minecraft:acacia_log":3,"minecraft:hopper":8,"minecraft:oxeye_daisy":1,"minecraft:nether_wart":12,"minecraft:tall_seagrass":8,"minecraft:magma_block":79,"minecraft:fire":146,"minecraft:cobbled_deepslate":118,"minecraft:moss_carpet":3,"minecraft:pumpkin":30,"minecraft:deepslate_lapis_ore":61,"minecraft:fletching_table":2,"minecraft:enchanting_table":1,"minecraft:twisting_vines":5,"minecraft:water_cauldron":2,"minecraft:dirt_path":25,"minecraft:spruce_pressure_plate":1,"minecraft:iron_block":33,"minecraft:white_banner":2,"minecraft:cut_sandstone":2,"minecraft:brown_mushroom":35,"minecraft:kelp_plant":48,"minecraft:torch":31,"minecraft:spruce_wall_sign":1,"minecraft:sugar_cane":439,"minecraft:wheat":623,"minecraft:stone_brick_stairs":8,"minecraft:loom":2,"minecraft:stonecutter":2,"minecraft:deepslate":677,"minecraft:mossy_cobblestone":91,"minecraft:cherry_sapling":1,"minecraft:jack_o_lantern":3,"minecraft:nether_bricks":126,"minecraft:cobbled_deepslate_slab":16,"minecraft:spruce_fence":117,"minecraft:jungle_planks":1,"minecraft:moss_block":17,"minecraft:kelp":56,"minecraft:suspicious_sand":1,"minecraft:andesite":43,"minecraft:diamond_block":2,"minecraft:potatoes":185,"minecraft:cobblestone_slab":190,"minecraft:warped_stem":25,"minecraft:potted_spruce_sapling":1,"minecraft:bamboo_sapling":1,"minecraft:bamboo":2,"minecraft:ender_chest":63,"minecraft:smithing_table":4,"minecraft:glass_pane":35,"minecraft:soul_sand":38,"minecraft:dandelion":4,"minecraft:short_grass":169,"minecraft:warped_roots":4,"minecraft:campfire":2,"minecraft:copper_ore":13,"minecraft:tall_grass":24,"minecraft:deepslate_gold_ore":93,"minecraft:diorite":60,"minecraft:big_dripleaf":10,"minecraft:warped_wart_block":6,"minecraft:purple_bed":21,"minecraft:cobblestone_wall":10,"minecraft:white_carpet":6,"minecraft:spruce_log":2937,"minecraft:birch_leaves":19,"minecraft:red_wall_banner":8,"minecraft:gravel":59,"minecraft:cobweb":1,"minecraft:acacia_planks":10,"minecraft:stone_bricks":68,"minecraft:chipped_anvil":2,"minecraft:fern":15,"minecraft:spruce_planks":268,"minecraft:farmland":1,"minecraft:cobbled_deepslate_stairs":13,"minecraft:cobblestone_stairs":27,"minecraft:brewing_stand":9,"minecraft:spruce_trapdoor":293,"minecraft:grass_block":2636,"minecraft:glowstone":39,"minecraft:iron_ore":6,"minecraft:anvil":2,"minecraft:azalea":1,"minecraft:spruce_slab":84,"minecraft:blackstone":25,"minecraft:twisting_vines_plant":11,"minecraft:clay":46,"minecraft:poppy":7,"minecraft:beacon":1,"minecraft:chest":20,"minecraft:cobblestone":951,"minecraft:nether_quartz_ore":196,"minecraft:grindstone":2,"minecraft:oak_planks":19,"minecraft:wall_torch":19,"minecraft:seagrass":11,"minecraft:warped_nylium":24,"minecraft:dark_oak_slab":1,"minecraft:birch_log":3,"minecraft:blue_ice":57,"minecraft:tnt":43,"minecraft:oak_log":48,"minecraft:sand":326,"minecraft:dirt":741,"minecraft:ancient_debris":26,"minecraft:netherrack":6604,"minecraft:oak_leaves":49,"minecraft:nether_gold_ore":149,"minecraft:tuff":20,"minecraft:dark_oak_leaves":13,"minecraft:deepslate_diamond_ore":111,"minecraft:mangrove_roots":1,"minecraft:ladder":26,"minecraft:spruce_leaves":345,"minecraft:mangrove_propagule":9,"minecraft:large_fern":28,"minecraft:oak_trapdoor":1,"minecraft:spruce_sapling":1,"minecraft:furnace":9,"minecraft:carrots":2284,"minecraft:gold_block":1,"minecraft:bell":1,"minecraft:nether_brick_fence":3,"minecraft:bookshelf":334,"minecraft:deepslate_iron_ore":28,"minecraft:packed_ice":50,"minecraft:stone":1182,"minecraft:flowering_azalea":4,"minecraft:basalt":55,"minecraft:spruce_door":21,"minecraft:oak_fence":3,"minecraft:crafting_table":14,"minecraft:lectern":71,"minecraft:stone_slab":8,"minecraft:lapis_ore":6,"minecraft:blue_bed":21,"minecraft:spruce_stairs":35,"minecraft:ice":797,"minecraft:sweet_berry_bush":91,"minecraft:white_wall_banner":3,"minecraft:bee_nest":1,"minecraft:coal_ore":145,"minecraft:cherry_leaves":1,"minecraft:cracked_stone_bricks":4,"minecraft:mossy_stone_bricks":2},"minecraft:dropped":{"minecraft:iron_sword":1,"minecraft:lapis_lazuli":275,"minecraft:cooked_beef":20,"minecraft:glass_bottle":3,"minecraft:diamond":157,"minecraft:crafting_table":4,"minecraft:cooked_porkchop":54,"minecraft:crossbow":12,"minecraft:warped_roots":19,"minecraft:cracked_stone_bricks":9,"minecraft:emerald":15,"minecraft:dirt":147,"minecraft:yellow_dye":6,"minecraft:gold_nugget":94,"minecraft:wooden_sword":1,"minecraft:bone_meal":821,"minecraft:phantom_membrane":4,"minecraft:sand":78,"minecraft:sugar":2,"minecraft:white_wool":10,"minecraft:bone":1934,"minecraft:sugar_cane":25,"minecraft:ancient_debris":5,"minecraft:cooked_chicken":1,"minecraft:golden_chestplate":2,"minecraft:cobbled_deepslate":90,"minecraft:wheat":3,"minecraft:obsidian":71,"minecraft:rotten_flesh":1392,"minecraft:oak_planks":41,"minecraft:glowstone_dust":2,"minecraft:blaze_powder":2,"minecraft:warped_planks":92,"minecraft:salmon":1,"minecraft:eye_armor_trim_smithing_template":1,"minecraft:tipped_arrow":1,"minecraft:hopper":4,"minecraft:leather_boots":1,"minecraft:ladder":2,"minecraft:leather_leggings":1,"minecraft:beef":9,"minecraft:warped_wart_block":3,"minecraft:ghast_tear":3,"minecraft:enchanted_book":11,"minecraft:iron_ingot":55,"minecraft:wheat_seeds":46,"minecraft:tnt":74,"minecraft:deepslate_diamond_ore":23,"minecraft:feather":2,"minecraft:book":358,"minecraft:oak_fence":5,"minecraft:cobblestone":269,"minecraft:iron_helmet":2,"minecraft:granite":5,"minecraft:coal":101,"minecraft:pufferfish":2,"minecraft:oxeye_daisy":1,"minecraft:golden_carrot":163,"minecraft:lapis_ore":6,"minecraft:diamond_helmet":2,"minecraft:rib_armor_trim_smithing_template":1,"minecraft:potion":6,"minecraft:white_banner":5,"minecraft:red_dye":11,"minecraft:mud":13,"minecraft:string":60,"minecraft:acacia_planks":8,"minecraft:spruce_sapling":36,"minecraft:snow_block":6,"minecraft:furnace":6,"minecraft:netherite_ingot":2,"minecraft:stone_sword":2,"minecraft:cobblestone_wall":2,"minecraft:deepslate":85,"minecraft:red_banner":3,"minecraft:chicken":23,"minecraft:stone_slab":12,"minecraft:cobbled_deepslate_slab":89,"minecraft:spruce_fence":1,"minecraft:nether_bricks":5,"minecraft:lily_of_the_valley":1,"minecraft:diamond_sword":10,"minecraft:cobblestone_slab":9,"minecraft:potato":25,"minecraft:spruce_boat":1,"minecraft:stone":416,"minecraft:spruce_trapdoor":19,"minecraft:spruce_planks":146,"minecraft:diamond_pickaxe":8,"minecraft:stone_bricks":15,"minecraft:spider_eye":58,"minecraft:bamboo":21,"minecraft:birch_boat":1,"minecraft:bow":194,"minecraft:bell":1,"minecraft:magma_block":82,"minecraft:warped_stem":2,"minecraft:soul_sand":19,"minecraft:brown_mushroom":1,"minecraft:birch_planks":3,"minecraft:diamond_axe":6,"minecraft:orange_dye":1,"minecraft:warped_fungus":1,"minecraft:baked_potato":61,"minecraft:ender_pearl":103,"minecraft:netherite_upgrade_smithing_template":2,"minecraft:flower_banner_pattern":10,"minecraft:leather":133,"minecraft:jungle_planks":2,"minecraft:cobblestone_stairs":2,"minecraft:flint":13,"minecraft:spruce_leaves":12,"minecraft:deepslate_gold_ore":87,"minecraft:packed_ice":2,"minecraft:netherite_scrap":2,"minecraft:ice":7,"minecraft:mutton":16,"minecraft:cut_sandstone":2,"minecraft:gold_ingot":21,"minecraft:cauldron":4,"minecraft:gravel":49,"minecraft:blackstone":32,"minecraft:mangrove_roots":1,"minecraft:twisting_vines":26,"minecraft:diamond_shovel":1,"minecraft:cooked_mutton":1,"minecraft:carrot":191,"minecraft:poppy":2,"minecraft:rabbit_hide":1,"minecraft:leather_chestplate":2,"minecraft:gunpowder":722,"minecraft:chest":2,"minecraft:bee_nest":2,"minecraft:basalt":41,"minecraft:arrow":2467,"minecraft:quartz":314,"minecraft:splash_potion":6,"minecraft:netherrack":3377,"minecraft:water_bucket":16,"minecraft:stone_hoe":3,"minecraft:bread":223,"minecraft:golden_helmet":1,"minecraft:mossy_cobblestone":3,"minecraft:bookshelf":70,"minecraft:diamond_leggings":2,"minecraft:poisonous_potato":2,"minecraft:copper_ingot":1,"minecraft:grass_block":410,"minecraft:stick":223,"minecraft:diorite":46,"minecraft:torch":213,"minecraft:iron_axe":3,"minecraft:redstone":13,"minecraft:sweet_berries":21,"minecraft:kelp":837,"minecraft:warped_nylium":21,"minecraft:ender_chest":1,"minecraft:blaze_rod":139,"minecraft:tuff":10,"minecraft:composter":1,"minecraft:flint_and_steel":1,"minecraft:copper_ore":1,"minecraft:filled_map":3,"minecraft:shield":1,"minecraft:diamond_chestplate":2,"minecraft:andesite":23,"minecraft:mossy_stone_bricks":4,"minecraft:purple_bed":1,"minecraft:golden_leggings":1,"minecraft:oak_boat":2,"minecraft:oak_sapling":1,"minecraft:golden_sword":2,"minecraft:diamond_boots":3,"minecraft:spruce_log":6,"minecraft:stone_pickaxe":1,"minecraft:wooden_pickaxe":1}},"DataVersion":3700}